{
  "sources": [
    {
      "title": "Decrypt",
      "feedUrl": "https://decrypt.co/feed",
      "siteUrl": "https://decrypt.co/feed",
      "articles": [
        {
          "id": "https://decrypt.co/?p=213494",
          "author": "Mathew Di Salvo",
          "description": "Bitcoin has taken a big hit over the past seven days following the launch of long-awaited spot Bitcoin ETFs on Wall Street.",
          "link": "https://decrypt.co/213494/this-week-in-coins-despite-etf-hype-bitcoin-and-ethereum-plunge-hard",
          "publishedOn": "2024-01-20T11:01:02.000Z",
          "wordCount": 9566,
          "title": "This Week in Coins: Despite ETF Hype, Bitcoin and Ethereum Plunge Hard",
          "enclosure": {
            "url": "https://img.decrypt.co/insecure/rs:fill:1024:512:1:0/plain/https://cdn.decrypt.co/wp-content/uploads/2021/02/Bitcoin-crash-gID_7.jpg@png",
            "length": "1000000",
            "type": "image/png"
          },
          "imageUrl": "https://img.decrypt.co/insecure/rs:fill:1024:512:1:0/plain/https://cdn.decrypt.co/wp-content/uploads/2021/02/Bitcoin-crash-gID_7.jpg@png"
        },
        {
          "id": "https://decrypt.co/?p=213592",
          "author": "Sander Lutz",
          "description": "A Colorado couple had their assets frozen by a state judge after making millions on a cryptocurrency they say they created at God’s command.",
          "link": "https://decrypt.co/213592/church-allegedly-issued-crypto-token-backed-nothing-but-gods-word",
          "publishedOn": "2024-01-19T23:21:34.000Z",
          "wordCount": 11358,
          "title": "Church Allegedly Issued Crypto Token Backed by Nothing But God's Word",
          "enclosure": {
            "url": "https://img.decrypt.co/insecure/rs:fill:1024:512:1:0/plain/https://cdn.decrypt.co/wp-content/uploads/2024/01/bitcoin-church-ai-gID_7.png@png",
            "length": "1000000",
            "type": "image/png"
          },
          "imageUrl": "https://img.decrypt.co/insecure/rs:fill:1024:512:1:0/plain/https://cdn.decrypt.co/wp-content/uploads/2024/01/bitcoin-church-ai-gID_7.png@png"
        },
        {
          "id": "https://decrypt.co/?p=213564",
          "author": "Mathew Di Salvo",
          "description": "Cash continues to flow out from Grayscale's Bitcoin ETF, while other funds see gains. Here's what's going on.",
          "link": "https://decrypt.co/213564/grayscale-sending-bitcoin-coinbase-500-million-why",
          "publishedOn": "2024-01-19T21:57:21.000Z",
          "wordCount": 10774,
          "title": "Grayscale Is Sending Bitcoin to Coinbase in $500 Million Clips—Here’s Why",
          "enclosure": {
            "url": "https://img.decrypt.co/insecure/rs:fill:1024:512:1:0/plain/https://cdn.decrypt.co/wp-content/uploads/2021/02/Webp.net-resizeimage29-gID_7.jpg@png",
            "length": "1000000",
            "type": "image/png"
          },
          "imageUrl": "https://img.decrypt.co/insecure/rs:fill:1024:512:1:0/plain/https://cdn.decrypt.co/wp-content/uploads/2021/02/Webp.net-resizeimage29-gID_7.jpg@png"
        },
        {
          "id": "https://decrypt.co/?p=147436",
          "author": "Jason Nelson",
          "description": "UPDATED: Final Fantasy maker Square Enix says it used AI tools for its big new game, plus Ubisoft is tapping Nvidia's gaming tech for NPCs.",
          "link": "https://decrypt.co/147436/ai-game-development-ubisoft-roblox-blizzard",
          "publishedOn": "2024-01-19T21:53:43.000Z",
          "wordCount": 12886,
          "title": "How Ubisoft, Xbox, and Blizzard Are Using AI to Make Next-Generation Games",
          "enclosure": {
            "url": "https://img.decrypt.co/insecure/rs:fill:1024:512:1:0/plain/https://cdn.decrypt.co/wp-content/uploads/2023/07/Decrypt-Wallpaper-Format-58-gID_7.png@png",
            "length": "1000000",
            "type": "image/png"
          },
          "imageUrl": "https://img.decrypt.co/insecure/rs:fill:1024:512:1:0/plain/https://cdn.decrypt.co/wp-content/uploads/2023/07/Decrypt-Wallpaper-Format-58-gID_7.png@png"
        },
        {
          "id": "https://decrypt.co/?p=213566",
          "author": "Andrew Throuvalas",
          "description": "Lawyers were impressed by Coinbase's oral arguments, and say full dismissal of the SEC's suit is a realistic possibility.",
          "link": "https://decrypt.co/213566/will-coinbase-win-dismissal-sec-lawsuit-legal-experts-weigh-in",
          "publishedOn": "2024-01-19T21:27:09.000Z",
          "wordCount": 11091,
          "title": "Will Coinbase Win Dismissal of SEC Lawsuit? Legal Experts Weigh In",
          "enclosure": {
            "url": "https://img.decrypt.co/insecure/rs:fill:1024:512:1:0/plain/https://cdn.decrypt.co/wp-content/uploads/2022/08/brian-armstrong-gary-gensler-gID_7.jpg@png",
            "length": "1000000",
            "type": "image/png"
          },
          "imageUrl": "https://img.decrypt.co/insecure/rs:fill:1024:512:1:0/plain/https://cdn.decrypt.co/wp-content/uploads/2022/08/brian-armstrong-gary-gensler-gID_7.jpg@png"
        },
        {
          "id": "https://decrypt.co/?p=213568",
          "author": "Jose Antonio Lanz",
          "description": "Bitcoin was the only asset besides the country’s own Ibovespa index approved for late night trading sessions.",
          "link": "https://decrypt.co/213568/brazil-stock-exchange-to-open-after-hours-trading-give-bitcoin-a-boost",
          "publishedOn": "2024-01-19T21:10:31.000Z",
          "wordCount": 10160,
          "title": "Brazil Stock Exchange to Open After Hours Trading, Give Bitcoin a Boost",
          "enclosure": {
            "url": "https://img.decrypt.co/insecure/rs:fill:1024:512:1:0/plain/https://cdn.decrypt.co/wp-content/uploads/2024/01/image-57-1-gID_7.png@png",
            "length": "1000000",
            "type": "image/png"
          },
          "imageUrl": "https://img.decrypt.co/insecure/rs:fill:1024:512:1:0/plain/https://cdn.decrypt.co/wp-content/uploads/2024/01/image-57-1-gID_7.png@png"
        },
        {
          "id": "https://decrypt.co/?p=211029",
          "author": "Andrew Hayward",
          "description": "UPDATED: Gaming airdrops are heating up, with Nifty Island, Nyan Heroes, and Apeiron revealing plans after the buzzy XAI token launch.",
          "link": "https://decrypt.co/211029/game-on-hottest-upcoming-gaming-token-airdrops",
          "publishedOn": "2024-01-19T20:26:16.000Z",
          "wordCount": 14533,
          "title": "Game On: The Hottest Upcoming Gaming Token Airdrops",
          "enclosure": {
            "url": "https://img.decrypt.co/insecure/rs:fill:1024:512:1:0/plain/https://cdn.decrypt.co/wp-content/uploads/2023/12/airdrop-giant-hand-gID_7.png@png",
            "length": "1000000",
            "type": "image/png"
          },
          "imageUrl": "https://img.decrypt.co/insecure/rs:fill:1024:512:1:0/plain/https://cdn.decrypt.co/wp-content/uploads/2023/12/airdrop-giant-hand-gID_7.png@png"
        },
        {
          "id": "https://decrypt.co/?p=213537",
          "author": "Jason Nelson",
          "description": "The global asset manager’s Bitcoin ETF is the latest in blockchain-related investment opportunities.",
          "link": "https://decrypt.co/213537/you-can-see-the-demand-out-there-for-bitcoin-franklin-templeton-ceo",
          "publishedOn": "2024-01-19T19:21:39.000Z",
          "wordCount": 11254,
          "title": "‘You Can See the Demand Out There for Bitcoin’: Franklin Templeton CEO",
          "enclosure": {
            "url": "https://img.decrypt.co/insecure/rs:fill:1024:512:1:0/plain/https://cdn.decrypt.co/wp-content/uploads/2024/01/Decrypt-Wallpaper-Format-2024-01-19T104938.356-gID_7.png@png",
            "length": "1000000",
            "type": "image/png"
          },
          "imageUrl": "https://img.decrypt.co/insecure/rs:fill:1024:512:1:0/plain/https://cdn.decrypt.co/wp-content/uploads/2024/01/Decrypt-Wallpaper-Format-2024-01-19T104938.356-gID_7.png@png"
        },
        {
          "id": "https://decrypt.co/?p=213540",
          "author": "Kate Irwin",
          "description": "Ronin’s mobile wallet for iOS and Android will see a new security feature as well as a refreshed design that lets users view more data about their crypto and NFTs.",
          "link": "https://decrypt.co/213540/ronin-gaming-wallet-now-supports-ethereum-polygon-bnb-chain",
          "publishedOn": "2024-01-19T19:06:21.000Z",
          "wordCount": 10163,
          "title": "Ronin Gaming Wallet Now Supports Ethereum, Polygon, and BNB Chain",
          "enclosure": {
            "url": "https://img.decrypt.co/insecure/rs:fill:1024:512:1:0/plain/https://cdn.decrypt.co/wp-content/uploads/2023/11/ronin-pixels-gID_7.png@png",
            "length": "1000000",
            "type": "image/png"
          },
          "imageUrl": "https://img.decrypt.co/insecure/rs:fill:1024:512:1:0/plain/https://cdn.decrypt.co/wp-content/uploads/2023/11/ronin-pixels-gID_7.png@png"
        },
        {
          "id": "https://decrypt.co/?p=197793",
          "author": "Andrew Hayward",
          "description": "UPDATED: Hundreds of developers admit in a major industry survey that they're working on Nintendo Switch 2 games. Here's everything we know so far.",
          "link": "https://decrypt.co/197793/nintendo-switch-2-rumors-leaks-latest-news",
          "publishedOn": "2024-01-19T18:13:38.000Z",
          "wordCount": 18228,
          "title": "Nintendo Switch 2 Preview: Everything You Need to Know",
          "enclosure": {
            "url": "https://img.decrypt.co/insecure/rs:fill:1024:512:1:0/plain/https://cdn.decrypt.co/wp-content/uploads/2023/09/nintendo-switch-shutterstock-gID_7.png@png",
            "length": "1000000",
            "type": "image/png"
          },
          "imageUrl": "https://img.decrypt.co/insecure/rs:fill:1024:512:1:0/plain/https://cdn.decrypt.co/wp-content/uploads/2023/09/nintendo-switch-shutterstock-gID_7.png@png"
        },
        {
          "id": "https://decrypt.co/?p=213528",
          "author": "Andrew Hayward",
          "description": "Upcoming gaming network Saga is bringing its play-to-airdrop push to games like Parallel, Shrapnel, and Gas Hero on other chains.",
          "link": "https://decrypt.co/213528/saga-expands-airdrop-rewards-solana-polygon-avalanche-games",
          "publishedOn": "2024-01-19T18:08:53.000Z",
          "wordCount": 9956,
          "title": "Saga Expands Airdrop Rewards to Solana, Polygon, and Avalanche Games",
          "enclosure": {
            "url": "https://img.decrypt.co/insecure/rs:fill:1024:512:1:0/plain/https://cdn.decrypt.co/wp-content/uploads/2023/12/gaming-shutterstock-gID_7.png@png",
            "length": "1000000",
            "type": "image/png"
          },
          "imageUrl": "https://img.decrypt.co/insecure/rs:fill:1024:512:1:0/plain/https://cdn.decrypt.co/wp-content/uploads/2023/12/gaming-shutterstock-gID_7.png@png"
        },
        {
          "id": "https://decrypt.co/?p=213511",
          "author": "Mathew Di Salvo",
          "description": "Bitcoin is down bad—but major altcoins like Solana, Avalanche, and Cardano are also experiencing a brutal selloff.",
          "link": "https://decrypt.co/213511/solana-avalanche-tumble-bitcoin-slides-towards-40000",
          "publishedOn": "2024-01-19T17:34:46.000Z",
          "wordCount": 9967,
          "title": "Solana, Avalanche Tumble as Bitcoin Slides Towards $40,000",
          "enclosure": {
            "url": "https://img.decrypt.co/insecure/rs:fill:1024:512:1:0/plain/https://cdn.decrypt.co/wp-content/uploads/2021/07/bear-market-red-gID_7.jpg@png",
            "length": "1000000",
            "type": "image/png"
          },
          "imageUrl": "https://img.decrypt.co/insecure/rs:fill:1024:512:1:0/plain/https://cdn.decrypt.co/wp-content/uploads/2021/07/bear-market-red-gID_7.jpg@png"
        },
        {
          "id": "https://decrypt.co/?p=213478",
          "author": "Jason Nelson",
          "description": "The 2024 presidential hopeful’s latest project involves 200 NFTs inscribed on the Bitcoin blockchain.",
          "link": "https://decrypt.co/213478/trump-is-doing-bitcoin-ordinals-as-he-tries-to-revive-flailing-nft-drop",
          "publishedOn": "2024-01-19T12:01:02.000Z",
          "wordCount": 10344,
          "title": "Trump Dips Into Bitcoin Ordinals as His NFT Ambitions Fizzle",
          "enclosure": {
            "url": "https://img.decrypt.co/insecure/rs:fill:1024:512:1:0/plain/https://cdn.decrypt.co/wp-content/uploads/2023/08/Donald-Trump-shutterstock_389315509-16x9-1-gID_7.jpg@png",
            "length": "1000000",
            "type": "image/png"
          },
          "imageUrl": "https://img.decrypt.co/insecure/rs:fill:1024:512:1:0/plain/https://cdn.decrypt.co/wp-content/uploads/2023/08/Donald-Trump-shutterstock_389315509-16x9-1-gID_7.jpg@png"
        },
        {
          "id": "https://decrypt.co/?p=213480",
          "author": "Stephen Graves",
          "description": "The SEC has stated it needs \"sufficient time to consider the proposed rule change and the issues raised therein.\"",
          "link": "https://decrypt.co/213480/sec-punts-fidelty-spot-ethereum-etf-decision-to-march",
          "publishedOn": "2024-01-19T11:04:12.000Z",
          "wordCount": 10573,
          "title": "SEC Punts Fidelty Spot Ethereum ETF Decision to March",
          "enclosure": {
            "url": "https://img.decrypt.co/insecure/rs:fill:1024:512:1:0/plain/https://cdn.decrypt.co/wp-content/uploads/2022/08/ethereum-merge-coinbase-crypto-exchanges-gID_7.jpeg@png",
            "length": "1000000",
            "type": "image/png"
          },
          "imageUrl": "https://img.decrypt.co/insecure/rs:fill:1024:512:1:0/plain/https://cdn.decrypt.co/wp-content/uploads/2022/08/ethereum-merge-coinbase-crypto-exchanges-gID_7.jpeg@png"
        },
        {
          "id": "https://decrypt.co/?p=213470",
          "author": "Jason Nelson",
          "description": "FTX tipped the scales in the amount of illicit cryptocurrency reported after the conviction of Sam Bankman-Fried.",
          "link": "https://decrypt.co/213470/crypto-crime-down-29-percent-in-2023-chainalysis-report",
          "publishedOn": "2024-01-19T01:00:44.000Z",
          "wordCount": 10616,
          "title": "Crypto Crime Down 29% in 2023: Chainalysis Report",
          "enclosure": {
            "url": "https://img.decrypt.co/insecure/rs:fill:1024:512:1:0/plain/https://cdn.decrypt.co/wp-content/uploads/2022/08/hackers-shutterstock-gID_7.png@png",
            "length": "1000000",
            "type": "image/png"
          },
          "imageUrl": "https://img.decrypt.co/insecure/rs:fill:1024:512:1:0/plain/https://cdn.decrypt.co/wp-content/uploads/2022/08/hackers-shutterstock-gID_7.png@png"
        },
        {
          "id": "https://decrypt.co/?p=213423",
          "author": "Kate Irwin",
          "description": "PREVIEW: Our first hands-on playtest of Nifty Island’s public beta was surprisingly addicting, allowing tons of room for imagination.",
          "link": "https://decrypt.co/213423/nifty-island-already-better-most-nft-sandbox-games",
          "publishedOn": "2024-01-18T23:24:14.000Z",
          "wordCount": 12322,
          "title": "'Nifty Island' Is Already Better Than Most NFT Sandbox Games",
          "enclosure": {
            "url": "https://img.decrypt.co/insecure/rs:fill:1024:512:1:0/plain/https://cdn.decrypt.co/wp-content/uploads/2024/01/Nifty-Island-2-gID_7.png@png",
            "length": "1000000",
            "type": "image/png"
          },
          "imageUrl": "https://img.decrypt.co/insecure/rs:fill:1024:512:1:0/plain/https://cdn.decrypt.co/wp-content/uploads/2024/01/Nifty-Island-2-gID_7.png@png"
        },
        {
          "id": "https://decrypt.co/?p=213457",
          "author": "Andrew Hayward",
          "description": "There’s one less Solana Saga in the world after a viral experiment... but 3,333 more NFTs commemorating it.",
          "link": "https://decrypt.co/213457/someone-microwaved-solana-saga-phone-now-degens-buying-meme-nfts",
          "publishedOn": "2024-01-18T23:06:53.000Z",
          "wordCount": 10143,
          "title": "Someone Microwaved a Solana Saga Phone—Now Degens Are Buying Meme NFTs",
          "enclosure": {
            "url": "https://img.decrypt.co/insecure/rs:fill:1024:512:1:0/plain/https://cdn.decrypt.co/wp-content/uploads/2024/01/solana-microwave-gID_7.png@png",
            "length": "1000000",
            "type": "image/png"
          },
          "imageUrl": "https://img.decrypt.co/insecure/rs:fill:1024:512:1:0/plain/https://cdn.decrypt.co/wp-content/uploads/2024/01/solana-microwave-gID_7.png@png"
        },
        {
          "id": "https://decrypt.co/?p=213442",
          "author": "Jose Antonio Lanz",
          "description": "The ARK Invest CEO says financial investors should go with crypto over the precious metal, and tech investors should stick with software.",
          "link": "https://decrypt.co/213442/bitcoin-is-coming-for-golds-global-market-says-cathie-wood",
          "publishedOn": "2024-01-18T22:45:17.000Z",
          "wordCount": 10894,
          "title": "Bitcoin Is Coming for Gold's Global Market, Says Cathie Wood",
          "enclosure": {
            "url": "https://img.decrypt.co/insecure/rs:fill:1024:512:1:0/plain/https://cdn.decrypt.co/wp-content/uploads/2024/01/Firefly-20240118183214-gID_7.png@png",
            "length": "1000000",
            "type": "image/png"
          },
          "imageUrl": "https://img.decrypt.co/insecure/rs:fill:1024:512:1:0/plain/https://cdn.decrypt.co/wp-content/uploads/2024/01/Firefly-20240118183214-gID_7.png@png"
        },
        {
          "id": "https://decrypt.co/?p=213440",
          "author": "Sander Lutz",
          "description": "Nathaniel Chastain was convicted last year for profiting off of information he was privy to as an executive at NFT marketplace OpenSea.",
          "link": "https://decrypt.co/213440/former-opensea-exec-argues-nft-insider-trading-conviction-violated-law",
          "publishedOn": "2024-01-18T22:21:38.000Z",
          "wordCount": 10292,
          "title": "Former OpenSea Exec Argues NFT Insider Trading Conviction Violated Law",
          "enclosure": {
            "url": "https://img.decrypt.co/insecure/rs:fill:1024:512:1:0/plain/https://cdn.decrypt.co/wp-content/uploads/2022/10/OpenSea-Justice-16x9-1-gID_7.jpg@png",
            "length": "1000000",
            "type": "image/png"
          },
          "imageUrl": "https://img.decrypt.co/insecure/rs:fill:1024:512:1:0/plain/https://cdn.decrypt.co/wp-content/uploads/2022/10/OpenSea-Justice-16x9-1-gID_7.jpg@png"
        },
        {
          "id": "https://decrypt.co/?p=213422",
          "author": "Mathew Di Salvo",
          "description": "BlackRock's Bitcoin ETF has broken records—but BTC's price is down bad since the historic launch of the long-awaited investment vehicles.",
          "link": "https://decrypt.co/213422/bitcoin-price-down-blackrock-1-billion-etf",
          "publishedOn": "2024-01-18T21:02:43.000Z",
          "wordCount": 10690,
          "title": "Bitcoin Plunges 12% in 7 Days as BlackRock Collects $1.1 Billion From ETF",
          "enclosure": {
            "url": "https://img.decrypt.co/insecure/rs:fill:1024:512:1:0/plain/https://cdn.decrypt.co/wp-content/uploads/2023/04/bitcoin-crash-gID_7.jpg@png",
            "length": "1000000",
            "type": "image/png"
          },
          "imageUrl": "https://img.decrypt.co/insecure/rs:fill:1024:512:1:0/plain/https://cdn.decrypt.co/wp-content/uploads/2023/04/bitcoin-crash-gID_7.jpg@png"
        },
        {
          "id": "https://decrypt.co/?p=213416",
          "author": "Andrew Hayward",
          "description": "Following last week’s XAI token airdrop, Arbitrum gaming network Xai will add Crypto Unicorns and related NFT games from Polygon.",
          "link": "https://decrypt.co/213416/crypto-unicorns-game-ditching-polygon-arbitrum-xai-network",
          "publishedOn": "2024-01-18T21:01:02.000Z",
          "wordCount": 10947,
          "title": "‘Crypto Unicorns’ Game Ditching Polygon for Arbitrum’s Xai Network",
          "enclosure": {
            "url": "https://img.decrypt.co/insecure/rs:fill:1024:512:1:0/plain/https://cdn.decrypt.co/wp-content/uploads/2024/01/crypto-unicorns-gID_7.jpeg@png",
            "length": "1000000",
            "type": "image/png"
          },
          "imageUrl": "https://img.decrypt.co/insecure/rs:fill:1024:512:1:0/plain/https://cdn.decrypt.co/wp-content/uploads/2024/01/crypto-unicorns-gID_7.jpeg@png"
        },
        {
          "id": "https://decrypt.co/?p=213411",
          "author": "Jason Nelson",
          "description": "84% of developers raise ethical concerns, with AAA studios more likely to have AI policies, according to Game Developer.",
          "link": "https://decrypt.co/213411/half-game-developers-use-ai-designers-worried-jobs",
          "publishedOn": "2024-01-18T20:51:40.000Z",
          "wordCount": 10823,
          "title": "Half of Game Devs Use AI, But Creatives Are Wary: Survey",
          "enclosure": {
            "url": "https://img.decrypt.co/insecure/rs:fill:1024:512:1:0/plain/https://cdn.decrypt.co/wp-content/uploads/2024/01/Decrypt-Wallpaper-Format-2024-01-18T121027.297-gID_7.png@png",
            "length": "1000000",
            "type": "image/png"
          },
          "imageUrl": "https://img.decrypt.co/insecure/rs:fill:1024:512:1:0/plain/https://cdn.decrypt.co/wp-content/uploads/2024/01/Decrypt-Wallpaper-Format-2024-01-18T121027.297-gID_7.png@png"
        },
        {
          "id": "https://decrypt.co/?p=213404",
          "author": "Andrew Hayward",
          "description": "Got $3,499 burning a hole in your pocket? The Apple Vision Pro is nearly here, and the first wave of orders are set to begin.",
          "link": "https://decrypt.co/213404/apple-vision-pro-preorders-begin-friday-what-need-know",
          "publishedOn": "2024-01-18T19:27:44.000Z",
          "wordCount": 10722,
          "title": "Apple Vision Pro Preorders Begin Friday—What You Need to Know",
          "enclosure": {
            "url": "https://img.decrypt.co/insecure/rs:fill:1024:512:1:0/plain/https://cdn.decrypt.co/wp-content/uploads/2023/06/apple-vision-pro-headset-gID_7.png@png",
            "length": "1000000",
            "type": "image/png"
          },
          "imageUrl": "https://img.decrypt.co/insecure/rs:fill:1024:512:1:0/plain/https://cdn.decrypt.co/wp-content/uploads/2023/06/apple-vision-pro-headset-gID_7.png@png"
        },
        {
          "id": "https://decrypt.co/?p=213393",
          "author": "Mathew Di Salvo",
          "description": "The stablecoin issuer continues to load up on Bitcoin.",
          "link": "https://decrypt.co/213393/tether-buys-more-bitcoin",
          "publishedOn": "2024-01-18T18:02:28.000Z",
          "wordCount": 10355,
          "title": "Tether Snaps Up More Bitcoin, Brings Holdings to $2.8 Billion",
          "enclosure": {
            "url": "https://img.decrypt.co/insecure/rs:fill:1024:512:1:0/plain/https://cdn.decrypt.co/wp-content/uploads/2023/07/tether-coins-usdt-stablecoin-gID_4.jpg@png",
            "length": "1000000",
            "type": "image/png"
          },
          "imageUrl": "https://img.decrypt.co/insecure/rs:fill:1024:512:1:0/plain/https://cdn.decrypt.co/wp-content/uploads/2023/07/tether-coins-usdt-stablecoin-gID_4.jpg@png"
        },
        {
          "id": "https://decrypt.co/?p=213380",
          "author": "Jose Antonio Lanz",
          "description": "Decentralized cryptocurrency exchange dYdX is hotter than ever, beating Uniswap v3 Ethereum in volume—and the charts back the hype.",
          "link": "https://decrypt.co/213380/defi-exchange-dydx-dethrones-ethereums-uniswap-as-token-outpaces-the-market",
          "publishedOn": "2024-01-18T18:00:16.000Z",
          "wordCount": 11023,
          "title": "DeFi Exchange dYdX Dethrones Ethereum's Uniswap as Token Outpaces the Market",
          "enclosure": {
            "url": "https://img.decrypt.co/insecure/rs:fill:1024:512:1:0/plain/https://cdn.decrypt.co/wp-content/uploads/2024/01/Firefly-20240118115514-2-gID_7.png@png",
            "length": "1000000",
            "type": "image/png"
          },
          "imageUrl": "https://img.decrypt.co/insecure/rs:fill:1024:512:1:0/plain/https://cdn.decrypt.co/wp-content/uploads/2024/01/Firefly-20240118115514-2-gID_7.png@png"
        },
        {
          "id": "https://decrypt.co/?p=213348",
          "author": "Andrew Hayward",
          "description": "Popular Ronin farming and social game Pixels is nearing its token launch as the current airdrop campaign winds down.",
          "link": "https://decrypt.co/213348/pixel-token-launch-very-close-pixels-game-airdrop",
          "publishedOn": "2024-01-18T16:41:05.000Z",
          "wordCount": 10874,
          "title": "PIXEL Token Launch 'Very Close' as Pixels Game Sets Play-to-Airdrop End",
          "enclosure": {
            "url": "https://img.decrypt.co/insecure/rs:fill:1024:512:1:0/plain/https://cdn.decrypt.co/wp-content/uploads/2024/01/pixels-airdrop-gID_7.jpeg@png",
            "length": "1000000",
            "type": "image/png"
          },
          "imageUrl": "https://img.decrypt.co/insecure/rs:fill:1024:512:1:0/plain/https://cdn.decrypt.co/wp-content/uploads/2024/01/pixels-airdrop-gID_7.jpeg@png"
        },
        {
          "id": "https://decrypt.co/?p=213327",
          "author": "Stephen Graves",
          "description": "Under the new rules, crypto firms in the European Union would need to conduct due diligence checks on transactions over €1,000.",
          "link": "https://decrypt.co/213327/eu-provisionally-agrees-tougher-aml-rules-for-crypto-firms",
          "publishedOn": "2024-01-18T13:03:41.000Z",
          "wordCount": 9529,
          "title": "EU Provisionally Agrees Tougher AML Rules for Crypto Firms",
          "enclosure": {
            "url": "https://img.decrypt.co/insecure/rs:fill:1024:512:1:0/plain/https://cdn.decrypt.co/wp-content/uploads/2023/06/eu-gID_7.jpg@png",
            "length": "1000000",
            "type": "image/png"
          },
          "imageUrl": "https://img.decrypt.co/insecure/rs:fill:1024:512:1:0/plain/https://cdn.decrypt.co/wp-content/uploads/2023/06/eu-gID_7.jpg@png"
        },
        {
          "id": "https://decrypt.co/?p=213312",
          "author": "Jose Antonio Lanz",
          "description": "A modular blockchain with a notorious founder is the new obsession among crypto enthusiasts, its token value up 40% since December 18.",
          "link": "https://decrypt.co/213312/what-is-celestia-tia-the-coin-created-by-a-cia-hacker-spiked-800-in-3-months",
          "publishedOn": "2024-01-18T12:01:02.000Z",
          "wordCount": 10721,
          "title": "What is Celestia (TIA)? The Coin Created by a CIA Hacker Spikes 800%",
          "enclosure": {
            "url": "https://img.decrypt.co/insecure/rs:fill:1024:512:1:0/plain/https://cdn.decrypt.co/wp-content/uploads/2024/01/Celestia-AI-Art-gID_7.png@png",
            "length": "1000000",
            "type": "image/png"
          },
          "imageUrl": "https://img.decrypt.co/insecure/rs:fill:1024:512:1:0/plain/https://cdn.decrypt.co/wp-content/uploads/2024/01/Celestia-AI-Art-gID_7.png@png"
        },
        {
          "id": "https://decrypt.co/?p=213324",
          "author": "Stephen Graves",
          "description": "In a campaign speech in New Hampshire, the former U.S. President called central bank digital currencies \"government tyranny.\"",
          "link": "https://decrypt.co/213324/trump-vows-to-never-allow-u-s-cbdc-if-reelected",
          "publishedOn": "2024-01-18T10:54:16.000Z",
          "wordCount": 9343,
          "title": "Trump Vows to 'Never Allow' U.S. CBDC if Reelected",
          "enclosure": {
            "url": "https://img.decrypt.co/insecure/rs:fill:1024:512:1:0/plain/https://cdn.decrypt.co/wp-content/uploads/2020/06/donald-trump-twitter-censorship-warnings-crypto-gID_7.jpg@png",
            "length": "1000000",
            "type": "image/png"
          },
          "imageUrl": "https://img.decrypt.co/insecure/rs:fill:1024:512:1:0/plain/https://cdn.decrypt.co/wp-content/uploads/2020/06/donald-trump-twitter-censorship-warnings-crypto-gID_7.jpg@png"
        },
        {
          "id": "https://decrypt.co/?p=213281",
          "author": "Jason Nelson",
          "description": "The investment giant highlighted Solana's vision and Ethereum's ecosystem in its bullish Twitter thread.",
          "link": "https://decrypt.co/213281/franklin-templeton-layer-one-ethereum-solana-after-bitcoin",
          "publishedOn": "2024-01-18T03:08:00.000Z",
          "wordCount": 10937,
          "title": "Laser-Eyed Franklin Templeton Sets Sights on Ethereum, Solana After Bitcoin",
          "enclosure": {
            "url": "https://img.decrypt.co/insecure/rs:fill:1024:512:1:0/plain/https://cdn.decrypt.co/wp-content/uploads/2024/01/Decrypt-Wallpaper-Format-2024-01-17T151931.539-gID_7.png@png",
            "length": "1000000",
            "type": "image/png"
          },
          "imageUrl": "https://img.decrypt.co/insecure/rs:fill:1024:512:1:0/plain/https://cdn.decrypt.co/wp-content/uploads/2024/01/Decrypt-Wallpaper-Format-2024-01-17T151931.539-gID_7.png@png"
        },
        {
          "id": "https://decrypt.co/?p=213295",
          "author": "Andrew Hayward",
          "description": "Ronin’s latest big game has launched a play-to-airdrop campaign, letting users earn while playing and engaging online.",
          "link": "https://decrypt.co/213295/apeiron-god-game-begins-airdrop-rewards-ethereum-scaler-ronin",
          "publishedOn": "2024-01-18T00:34:33.000Z",
          "wordCount": 10272,
          "title": "‘Apeiron’ God Game Begins Airdrop Rewards on Ethereum Scaler Ronin",
          "enclosure": {
            "url": "https://img.decrypt.co/insecure/rs:fill:1024:512:1:0/plain/https://cdn.decrypt.co/wp-content/uploads/2024/01/apeiron-artwork-gID_7.jpeg@png",
            "length": "1000000",
            "type": "image/png"
          },
          "imageUrl": "https://img.decrypt.co/insecure/rs:fill:1024:512:1:0/plain/https://cdn.decrypt.co/wp-content/uploads/2024/01/apeiron-artwork-gID_7.jpeg@png"
        },
        {
          "id": "https://decrypt.co/?p=213275",
          "author": "Kate Irwin",
          "description": "Nifty Island, the create-an-island game with NFTs, is offering future token perks to active players who mint NFTs and create experiences.",
          "link": "https://decrypt.co/213275/nifty-island-nft-game-launches-open-beta-airdrop-rewards",
          "publishedOn": "2024-01-18T00:05:17.000Z",
          "wordCount": 11215,
          "title": "'Nifty Island' NFT Game Launches Open Beta With Airdrop Rewards",
          "enclosure": {
            "url": "https://img.decrypt.co/insecure/rs:fill:1024:512:1:0/plain/https://cdn.decrypt.co/wp-content/uploads/2024/01/Nifty-Island-1-gID_7.png@png",
            "length": "1000000",
            "type": "image/png"
          },
          "imageUrl": "https://img.decrypt.co/insecure/rs:fill:1024:512:1:0/plain/https://cdn.decrypt.co/wp-content/uploads/2024/01/Nifty-Island-1-gID_7.png@png"
        },
        {
          "id": "https://decrypt.co/?p=213288",
          "author": "Sander Lutz",
          "description": "U.S. District Judge Katherine Polk Failla will decide whether to dismiss the SEC’s lawsuit against the crypto exchange for alleged securities violations.",
          "link": "https://decrypt.co/213288/coinbase-case-judge-asks-if-sec-is-sweeping-too-broadly-as-she-weighs-dismissal",
          "publishedOn": "2024-01-17T23:52:14.000Z",
          "wordCount": 10854,
          "title": "Coinbase Case Judge Asks If SEC Is ‘Sweeping Too Broadly’ as She Weighs Dismissal",
          "enclosure": {
            "url": "https://img.decrypt.co/insecure/rs:fill:1024:512:1:0/plain/https://cdn.decrypt.co/wp-content/uploads/2023/02/Coinbase-shutterstock_2193646633-16x9-1-gID_7.jpg@png",
            "length": "1000000",
            "type": "image/png"
          },
          "imageUrl": "https://img.decrypt.co/insecure/rs:fill:1024:512:1:0/plain/https://cdn.decrypt.co/wp-content/uploads/2023/02/Coinbase-shutterstock_2193646633-16x9-1-gID_7.jpg@png"
        },
        {
          "id": "https://decrypt.co/?p=213274",
          "author": "Mathew Di Salvo",
          "description": "Bitcoin miners in Texas are curtailing power to ensure the stability of the state’s power grid.",
          "link": "https://decrypt.co/213274/bitcoin-hash-rate-tumbles-halving-approaches",
          "publishedOn": "2024-01-17T23:11:14.000Z",
          "wordCount": 10566,
          "title": "Bitcoin Hash Rate Tumbles as Halving Approaches",
          "enclosure": {
            "url": "https://img.decrypt.co/insecure/rs:fill:1024:512:1:0/plain/https://cdn.decrypt.co/wp-content/uploads/2023/04/bitcoin-mining-symbol-gID_7.jpeg@png",
            "length": "1000000",
            "type": "image/png"
          },
          "imageUrl": "https://img.decrypt.co/insecure/rs:fill:1024:512:1:0/plain/https://cdn.decrypt.co/wp-content/uploads/2023/04/bitcoin-mining-symbol-gID_7.jpeg@png"
        },
        {
          "id": "https://decrypt.co/?p=213268",
          "author": "Andrew Hayward",
          "description": "BONK isn’t the hottest Solana meme coin at the moment: WIF has more than doubled in price this week alone.",
          "link": "https://decrypt.co/213268/solana-meme-coin-dogwifhat-spikes-257-sol-reclaims-100",
          "publishedOn": "2024-01-17T21:31:48.000Z",
          "wordCount": 10072,
          "title": "Solana Meme Coin Dogwifhat Spikes 257% as SOL Reclaims $100",
          "enclosure": {
            "url": "https://img.decrypt.co/insecure/rs:fill:1024:512:1:0/plain/https://cdn.decrypt.co/wp-content/uploads/2023/12/dogwifhat-market-gID_7.png@png",
            "length": "1000000",
            "type": "image/png"
          },
          "imageUrl": "https://img.decrypt.co/insecure/rs:fill:1024:512:1:0/plain/https://cdn.decrypt.co/wp-content/uploads/2023/12/dogwifhat-market-gID_7.png@png"
        },
        {
          "id": "https://decrypt.co/?p=213244",
          "author": "Jose Antonio Lanz",
          "description": "Satya Nadella sees a future where AI agents acting on our behalf are at the core of our interactions with computers.",
          "link": "https://decrypt.co/213244/microsoft-ceo-rabbit-r1-ai-gadget-was-most-impressive-demo-since-steve-jobs-iphone-unveiling",
          "publishedOn": "2024-01-17T20:45:26.000Z",
          "wordCount": 10870,
          "title": "Microsoft CEO: Rabbit R1 AI Gadget Was ‘Most Impressive’ Demo Since Steve Jobs’ iPhone Unveiling",
          "enclosure": {
            "url": "https://img.decrypt.co/insecure/rs:fill:1024:512:1:0/plain/https://cdn.decrypt.co/wp-content/uploads/2024/01/Satya-Nadella-Rabbit-R1-iPhone-gID_7.jpg@png",
            "length": "1000000",
            "type": "image/png"
          },
          "imageUrl": "https://img.decrypt.co/insecure/rs:fill:1024:512:1:0/plain/https://cdn.decrypt.co/wp-content/uploads/2024/01/Satya-Nadella-Rabbit-R1-iPhone-gID_7.jpg@png"
        },
        {
          "id": "https://decrypt.co/videos/interviews/i3sesrao/are-you-the-one-being-farmed-w-frisson",
          "author": null,
          "description": "Reza is joined by Frisson from Tallyx.xyz\n\nThey reflect on:\n- building in the bear market\n- the points system meta\n- will zoomers care about decentralization",
          "link": "https://decrypt.co/videos/interviews/i3sesrao/are-you-the-one-being-farmed-w-frisson",
          "publishedOn": "2024-01-17T18:38:15.000Z",
          "wordCount": 6733,
          "title": "Are you the one being farmed? w/ Frisson",
          "enclosure": {
            "url": "https://cdn.jwplayer.com/v2/media/i3sesrao/poster.jpg",
            "length": "1000000",
            "type": "image/png"
          },
          "imageUrl": "https://cdn.jwplayer.com/v2/media/i3sesrao/poster.jpg"
        },
        {
          "id": "https://decrypt.co/videos/live-events/79jpGlCe/look-touch-own-oona-discusses-her-performance-art-exhibition",
          "author": null,
          "description": "Conceptual artist OONA joins moderator Raina Marie to discuss \"Look Touch Own,\" her performance art exhibition featuring her own former breast implants, which have been tokenized. This conversation was recorded at Rug Radio's R Haus event at Art Basel Miami in December 2023.",
          "link": "https://decrypt.co/videos/live-events/79jpGlCe/look-touch-own-oona-discusses-her-performance-art-exhibition",
          "publishedOn": "2024-01-17T16:45:00.000Z",
          "wordCount": 6833,
          "title": "'Look Touch Own': OONA Discusses Her Performance Art Exhibition",
          "enclosure": {
            "url": "https://cdn.jwplayer.com/v2/media/79jpGlCe/poster.jpg",
            "length": "1000000",
            "type": "image/png"
          },
          "imageUrl": "https://cdn.jwplayer.com/v2/media/79jpGlCe/poster.jpg"
        },
        {
          "id": "https://decrypt.co/videos/live-events/YiQgzWJW/genius-marketing-by-genius-marketers-how-crypto-builders-can-reach-the-masses",
          "author": null,
          "description": "Rug Radio founder Farokh Sarmad moderates a conversation between 9dcc founder and CEO Gmoney and Serotonin founder and CEO Amanda Cassatt about the challenges and opportunities in Web3 marketing and how they're navigating the ever-evolving space. Recorded at Rug Radio's R Haus event at Art Basel Miami in December 2023.",
          "link": "https://decrypt.co/videos/live-events/YiQgzWJW/genius-marketing-by-genius-marketers-how-crypto-builders-can-reach-the-masses",
          "publishedOn": "2024-01-17T16:40:00.000Z",
          "wordCount": 6886,
          "title": "Genius Marketing by Genius Marketers: How Crypto Builders Can Reach the Masses",
          "enclosure": {
            "url": "https://cdn.jwplayer.com/v2/media/YiQgzWJW/poster.jpg",
            "length": "1000000",
            "type": "image/png"
          },
          "imageUrl": "https://cdn.jwplayer.com/v2/media/YiQgzWJW/poster.jpg"
        },
        {
          "id": "https://decrypt.co/videos/live-events/GK3aN0zo/generative-art-across-mediums-artists-discuss-the-evolving-space",
          "author": null,
          "description": "In this panel discussion from Rug Radio's R Haus at Art Basel Miami 2023, Sofia Garcia, Ismail Tazi, Emily Edelman, and Aleksandra Art discuss the expanding generative art space—and why \"generative\" doesn't necessarily have to mean digital.",
          "link": "https://decrypt.co/videos/live-events/GK3aN0zo/generative-art-across-mediums-artists-discuss-the-evolving-space",
          "publishedOn": "2024-01-12T02:45:00.000Z",
          "wordCount": 6803,
          "title": "Generative Art Across Mediums: Artists Discuss the Evolving Space",
          "enclosure": {
            "url": "https://cdn.jwplayer.com/v2/media/GK3aN0zo/poster.jpg",
            "length": "1000000",
            "type": "image/png"
          },
          "imageUrl": "https://cdn.jwplayer.com/v2/media/GK3aN0zo/poster.jpg"
        },
        {
          "id": "https://decrypt.co/videos/interviews/rkYpU8TJ/the-ai-coin-to-rule-them-all-with-mike-grantis",
          "author": null,
          "description": "Reza is joined by Mike Grantis from Contango Digital to discuss\n- The AI coin to rule them all\n- The Solana Ecosystem \n- What's next for Solana airdrops",
          "link": "https://decrypt.co/videos/interviews/rkYpU8TJ/the-ai-coin-to-rule-them-all-with-mike-grantis",
          "publishedOn": "2024-01-10T18:46:26.000Z",
          "wordCount": 6873,
          "title": "The AI Coin to Rule Them All with Mike Grantis",
          "enclosure": {
            "url": "https://cdn.jwplayer.com/v2/media/rkYpU8TJ/poster.jpg",
            "length": "1000000",
            "type": "image/png"
          },
          "imageUrl": "https://cdn.jwplayer.com/v2/media/rkYpU8TJ/poster.jpg"
        },
        {
          "id": "https://decrypt.co/videos/live-events/DcrU04gG/conversation-with-snowfro-bringing-chromie-squiggle-8107-to-the-physical-space",
          "author": null,
          "description": "Art Blocks founder and CEO and \"Chromie Squiggle\" project creator Erick \"snowfro\" Calderon spoke with Benny Redbeard Gross at Rug Radio's R Haus event at Art Basel 2023, to discuss how and why \"Chromie Squiggle\" NFT #8107 was given a special edition print run in collaboration with Avant Arte.",
          "link": "https://decrypt.co/videos/live-events/DcrU04gG/conversation-with-snowfro-bringing-chromie-squiggle-8107-to-the-physical-space",
          "publishedOn": "2024-01-10T18:40:00.000Z",
          "wordCount": 6875,
          "title": "Conversation With Snowfro: Bringing 'Chromie Squiggle' #8107 to the Physical Space",
          "enclosure": {
            "url": "https://cdn.jwplayer.com/v2/media/DcrU04gG/poster.jpg",
            "length": "1000000",
            "type": "image/png"
          },
          "imageUrl": "https://cdn.jwplayer.com/v2/media/DcrU04gG/poster.jpg"
        },
        {
          "id": "https://decrypt.co/videos/interviews/34Oil4Qu/dont-underestimate-mobile-gaming-qualcomms-matthew-grossman",
          "author": null,
          "description": "Qualcomm product marketing manager Matthew Grossman tells Decrypt's Kate Irwin why mobile esports is exploding in popularity around the world—and dispels some of the misconceptions around mobile gaming.",
          "link": "https://decrypt.co/videos/interviews/34Oil4Qu/dont-underestimate-mobile-gaming-qualcomms-matthew-grossman",
          "publishedOn": "2024-01-08T18:10:00.000Z",
          "wordCount": 6744,
          "title": "Don't Underestimate Mobile Gaming: Qualcomm's Matthew Grossman",
          "enclosure": {
            "url": "https://cdn.jwplayer.com/v2/media/34Oil4Qu/poster.jpg",
            "length": "1000000",
            "type": "image/png"
          },
          "imageUrl": "https://cdn.jwplayer.com/v2/media/34Oil4Qu/poster.jpg"
        },
        {
          "id": "https://decrypt.co/videos/interviews/VOX04ytt/bitcoin-etf-this-is-the-calm-before-the-storm-says-etf-analyst",
          "author": null,
          "description": "Bloomberg Senior ETF Analyst Eric Balchunas joins Farokh Sarmad, Michael Anderson, and Ovie Faruq on the FOMO Hour to share the latest intel on the looming approval for a spot Bitcoin ETF, what might happen when the very different worlds of TradFi and crypto collide, and his insights on “Genslish,” the unique and strategic language of SEC chair Gary Gensler.",
          "link": "https://decrypt.co/videos/interviews/VOX04ytt/bitcoin-etf-this-is-the-calm-before-the-storm-says-etf-analyst",
          "publishedOn": "2024-01-05T20:20:19.000Z",
          "wordCount": 6934,
          "title": "Bitcoin ETF: This Is the 'Calm Before the Storm', Says ETF Analyst",
          "enclosure": {
            "url": "https://cdn.jwplayer.com/v2/media/VOX04ytt/poster.jpg",
            "length": "1000000",
            "type": "image/png"
          },
          "imageUrl": "https://cdn.jwplayer.com/v2/media/VOX04ytt/poster.jpg"
        },
        {
          "id": "https://decrypt.co/videos/interviews/EfNuNu8a/losing-1500-btc-on-mt-gox-and-the-problem-with-women-in-web3",
          "author": null,
          "description": "This week our host is joined by Brooke Lacey! \n\nThey discuss:  \n- Making and losing generational wealth\n- Trauma Bond\n- Women in Web3\n- The Problem with WAGMI",
          "link": "https://decrypt.co/videos/interviews/EfNuNu8a/losing-1500-btc-on-mt-gox-and-the-problem-with-women-in-web3",
          "publishedOn": "2024-01-03T19:02:44.000Z",
          "wordCount": 6776,
          "title": "Losing 1500 BTC on Mt Gox and the Problem with Women in Web3",
          "enclosure": {
            "url": "https://cdn.jwplayer.com/v2/media/EfNuNu8a/poster.jpg",
            "length": "1000000",
            "type": "image/png"
          },
          "imageUrl": "https://cdn.jwplayer.com/v2/media/EfNuNu8a/poster.jpg"
        },
        {
          "id": "https://decrypt.co/videos/live-events/yvrs4lBx/esl-faceit-group-exploring-blockchain-opportunistically-says-exec",
          "author": null,
          "description": "Sam Braithwaite—ESL Faceit Group's VP of Game Ecosystems, Mobile, and Snapdragon Pro Series—shares the esports firm's approach to blockchain technology with GG's Kate Irwin.",
          "link": "https://decrypt.co/videos/live-events/yvrs4lBx/esl-faceit-group-exploring-blockchain-opportunistically-says-exec",
          "publishedOn": "2023-12-30T02:21:00.000Z",
          "wordCount": 6732,
          "title": "ESL Faceit Group Exploring Blockchain 'Opportunistically,' Says Exec",
          "enclosure": {
            "url": "https://cdn.jwplayer.com/v2/media/yvrs4lBx/poster.jpg",
            "length": "1000000",
            "type": "image/png"
          },
          "imageUrl": "https://cdn.jwplayer.com/v2/media/yvrs4lBx/poster.jpg"
        },
        {
          "id": "https://decrypt.co/videos/interviews/tAwP55g9/bryan-johnson-explains-his-quest-for-immortality-and-why-he-started-with-the-penis",
          "author": null,
          "description": "Billionaire biohacker Bryan Johnson shared with Decrypt's Jason Nelson why he began his longevity quest and how technology has shaped the endeavor. Johnson also discusses some of his controversial experiments.",
          "link": "https://decrypt.co/videos/interviews/tAwP55g9/bryan-johnson-explains-his-quest-for-immortality-and-why-he-started-with-the-penis",
          "publishedOn": "2023-12-24T19:38:39.000Z",
          "wordCount": 6796,
          "title": "Bryan Johnson Explains His Quest for Immortality and Why He Started with the Penis",
          "enclosure": {
            "url": "https://cdn.jwplayer.com/v2/media/tAwP55g9/poster.jpg",
            "length": "1000000",
            "type": "image/png"
          },
          "imageUrl": "https://cdn.jwplayer.com/v2/media/tAwP55g9/poster.jpg"
        },
        {
          "id": "https://decrypt.co/videos/live-events/TI3aFBhO/wildcards-plans-for-2024-with-founders-paul-and-katy-bettner",
          "author": null,
          "description": "Wildcard developers Paul and Katy Bettner tell Decrypt's Kate Irwin about why they see their game as a \"Web3 game,\" not a crypto game, and share why they've stuck with their initial vision despite the challenging broader market.",
          "link": "https://decrypt.co/videos/live-events/TI3aFBhO/wildcards-plans-for-2024-with-founders-paul-and-katy-bettner",
          "publishedOn": "2023-12-22T21:34:00.000Z",
          "wordCount": 6814,
          "title": "Wildcard's Plans for 2024 with Founders Paul and Katy Bettner",
          "enclosure": {
            "url": "https://cdn.jwplayer.com/v2/media/TI3aFBhO/poster.jpg",
            "length": "1000000",
            "type": "image/png"
          },
          "imageUrl": "https://cdn.jwplayer.com/v2/media/TI3aFBhO/poster.jpg"
        }
      ]
    },
    {
      "title": "News",
      "feedUrl": "https://cryptopanic.com/news/rss/",
      "siteUrl": "https://cryptopanic.com/",
      "articles": [
        {
          "id": "https://cryptopanic.com/news/19190115/Wiki-Finance-Expo-Hong-Kong-2024-Is-Coming-in-May",
          "author": null,
          "description": "Regulation, Forex, Crypto, Web 3.0, NFTs, Metaverse, ESG, AI Will Be in Focus.",
          "link": "https://cryptopanic.com/news/19190115/Wiki-Finance-Expo-Hong-Kong-2024-Is-Coming-in-May",
          "publishedOn": "2024-01-20T11:00:00.000Z",
          "wordCount": 598,
          "title": "Wiki Finance Expo Hong Kong 2024 Is Coming in May!",
          "imageUrl": "https://en.cryptonomist.ch/wp-content/uploads/2024/01/Wiki-Finance-Expo-Hong-Kong.jpg"
        },
        {
          "id": "https://cryptopanic.com/news/19190105/CRAZY-Bitcoin-To-EXPLODE-In-DAYS-Bitcoin-Is-An-Asset-That-Will-CREATE-WEALTH",
          "author": null,
          "description": "Ok, it looks like we've reached the pinnacle of near excessive excitement with this one... a very famous cryptocurrency Bitcoin perma-Bull has announced that he thinks bitcoin is about to skyrocket... but his time frame for the event is a bit... interesting. Michael Saylor has issued a warning...",
          "link": "https://cryptopanic.com/news/19190105/CRAZY-Bitcoin-To-EXPLODE-In-DAYS-Bitcoin-Is-An-Asset-That-Will-CREATE-WEALTH",
          "publishedOn": "2024-01-20T10:44:26.000Z",
          "wordCount": 603,
          "title": "CRAZY: Bitcoin To EXPLODE In DAYS & Bitcoin Is An Asset That Will CREATE WEALTH",
          "imageUrl": "https://i2.ytimg.com/vi/122KxiLlaPs/hqdefault.jpg"
        },
        {
          "id": "https://cryptopanic.com/news/19190106/Shiba-Inu-SHIB-Skyrockets-1173-as-Whales-Make-Intriguing-Move",
          "author": null,
          "description": "Shiba Inu (SHIB) rises 1,173% as whales embark on zero-eliminating mission",
          "link": "https://cryptopanic.com/news/19190106/Shiba-Inu-SHIB-Skyrockets-1173-as-Whales-Make-Intriguing-Move",
          "publishedOn": "2024-01-20T10:42:00.000Z",
          "wordCount": 598,
          "title": "Shiba Inu (SHIB) Skyrockets 1,173% as Whales Make Intriguing Move",
          "imageUrl": "https://u.today/sites/default/files/styles/twitter/public/2024-01/s1217.1.jpg"
        },
        {
          "id": "https://cryptopanic.com/news/19190103/Ripple-Presidents-vague-XRP-adoption-remarks-stir-concern",
          "author": null,
          "description": "Ripple president Monica Long‘s recent comments in an interview with the Chain Reaction Pod have sparked a wave of concern in the XRP community. The interview, which centered on the implications of the U.S. court ruling declaring XRP as not a security for retail investors, left many anticipating...",
          "link": "https://cryptopanic.com/news/19190103/Ripple-Presidents-vague-XRP-adoption-remarks-stir-concern",
          "publishedOn": "2024-01-20T10:41:04.000Z",
          "wordCount": 596,
          "title": "Ripple President’s vague XRP adoption remarks stir concern",
          "imageUrl": null
        },
        {
          "id": "https://cryptopanic.com/news/19190101/Crypto-Fraud-IcomTech-Ex-CEO-Gets-5-Years-Jail-For-Duping-Investors",
          "author": null,
          "description": "Justice caught up with crypto scam architect Marco Ruiz Ocho on Friday, as he received a five-year prison sentence for his role in orchestrating the IcomTech Ponzi scheme. The ruling marks a significant victory for investors swindled out of millions and serves as a stark warning to bad actors in...",
          "link": "https://cryptopanic.com/news/19190101/Crypto-Fraud-IcomTech-Ex-CEO-Gets-5-Years-Jail-For-Duping-Investors",
          "publishedOn": "2024-01-20T10:40:52.000Z",
          "wordCount": 599,
          "title": "Crypto Fraud: IcomTech Ex-CEO Gets 5 Years Jail For Duping Investors",
          "imageUrl": "https://bitcoinist.com/wp-content/uploads/2024/01/a_821d75.png"
        },
        {
          "id": "https://cryptopanic.com/news/19190076/Analyst-Identifies-MINA-ADA-SUI-and-DYDX-For-Interesting-Moves",
          "author": null,
          "description": "An Altcoin Daily host has identified four altcoins showing upside potential on the recent dip. The host thinks MINA, ADA, SUI, and DYDX will rally for various reasons. Bitcoin dropped by 18%, dragging the entire crypto market along after reaching a yearly high of $49,048. Bitcoin dropped by 18%,...",
          "link": "https://cryptopanic.com/news/19190076/Analyst-Identifies-MINA-ADA-SUI-and-DYDX-For-Interesting-Moves",
          "publishedOn": "2024-01-20T10:19:00.000Z",
          "wordCount": 598,
          "title": "Analyst Identifies MINA, ADA, SUI, and DYDX For “Interesting Moves”",
          "imageUrl": null
        },
        {
          "id": "https://cryptopanic.com/news/19190080/Jan3-CEO-Questions-Grayscales-Fee-Strategy-as-Bleeding-From-Its-Spot-Bitcoin-ETF-GBTC-Continuous-Hurting-Bitcoin",
          "author": null,
          "description": "",
          "link": "https://cryptopanic.com/news/19190080/Jan3-CEO-Questions-Grayscales-Fee-Strategy-as-Bleeding-From-Its-Spot-Bitcoin-ETF-GBTC-Continuous-Hurting-Bitcoin",
          "publishedOn": "2024-01-20T10:15:47.000Z",
          "wordCount": null,
          "title": "Jan3 CEO Questions Grayscale’s Fee Strategy as Bleeding From Its Spot Bitcoin ETF (GBTC) Continuous Hurting Bitcoin",
          "imageUrl": null
        },
        {
          "id": "https://cryptopanic.com/news/19190075/Cardano-Could-Explode-by-Over-1300-if-History-Repeats-Itself-According-to-Trader-But-Theres-a-Catch",
          "author": null,
          "description": "Cryptocurrency analyst and trader Ali Martinez is saying that Cardano (ADA) is on the cusp of potentially enjoying an explosive run from its current level. Martinez tells his 41,000 followers on the social media platform X that Cardano is currently in a consolidation phase on the three-day...",
          "link": "https://cryptopanic.com/news/19190075/Cardano-Could-Explode-by-Over-1300-if-History-Repeats-Itself-According-to-Trader-But-Theres-a-Catch",
          "publishedOn": "2024-01-20T10:15:03.000Z",
          "wordCount": 606,
          "title": "Cardano Could Explode by Over 1,300% if History Repeats Itself, According to Trader – But There’s a Catch",
          "imageUrl": "https://dailyhodl.com/wp-content/uploads/2024/01/History-Repeats-Itself-cardano.jpg"
        },
        {
          "id": "https://cryptopanic.com/news/19190060/Instant-Settlement-Series-The-Publishing-Industry",
          "author": null,
          "description": "The third part in an article series by Ivan Makedonski from Breez on how Lightning's instant settlement finality can be a disruptive force fundamentally changing how different industries are organized.",
          "link": "https://cryptopanic.com/news/19190060/Instant-Settlement-Series-The-Publishing-Industry",
          "publishedOn": "2024-01-20T10:00:00.000Z",
          "wordCount": 594,
          "title": "Instant Settlement Series: The Publishing Industry",
          "imageUrl": "http://bitcoinmagazine.com/.image/c_limit%2Ccs_srgb%2Ch_1200%2Cq_auto:good%2Cw_1200/MjAzNzU4MjQ5NDc0Nzk1MDY4/image2.png"
        },
        {
          "id": "https://cryptopanic.com/news/19190036/Coinbase-CEO-Brian-Armstrong-supports-Dimons-critical-Bitcoin-stance",
          "author": null,
          "description": "Brian Armstrong, the CEO of Coinbase, has come out in defense of Jamie Dimon, the CEO of JPMorgan Chase, following Dimon’s controversial remarks about Bitcoin. During the World Economic Forum in Davos, Dimon labeled Bitcoin as a “pet rock,” criticizing its legitimacy and utility. Despite the...",
          "link": "https://cryptopanic.com/news/19190036/Coinbase-CEO-Brian-Armstrong-supports-Dimons-critical-Bitcoin-stance",
          "publishedOn": "2024-01-20T09:58:28.000Z",
          "wordCount": 597,
          "title": "Coinbase CEO Brian Armstrong supports Dimon’s critical Bitcoin stance",
          "imageUrl": null
        },
        {
          "id": "https://cryptopanic.com/news/19190038/Bitcoin-Defends-41K-Level-Chainlink-Gains-5-Daily-Weekend-Watch",
          "author": null,
          "description": "",
          "link": "https://cryptopanic.com/news/19190038/Bitcoin-Defends-41K-Level-Chainlink-Gains-5-Daily-Weekend-Watch",
          "publishedOn": "2024-01-20T09:54:27.000Z",
          "wordCount": null,
          "title": "Bitcoin Defends $41K Level, Chainlink Gains 5% Daily (Weekend Watch)",
          "imageUrl": null
        },
        {
          "id": "https://cryptopanic.com/news/19190019/World-Economic-Forums-Reskilling-Revolution-A-Global-Leap-in-Education-and-Job-Opportunities",
          "author": null,
          "description": "",
          "link": "https://cryptopanic.com/news/19190019/World-Economic-Forums-Reskilling-Revolution-A-Global-Leap-in-Education-and-Job-Opportunities",
          "publishedOn": "2024-01-20T09:32:39.000Z",
          "wordCount": null,
          "title": "World Economic Forum’s Reskilling Revolution: A Global Leap in Education and Job Opportunities",
          "imageUrl": null
        },
        {
          "id": "https://cryptopanic.com/news/19190021/il-Capo-Comments-on-Bitcoin-and-Ethereum-Will-a-Bullish-Rally-Come",
          "author": null,
          "description": "",
          "link": "https://cryptopanic.com/news/19190021/il-Capo-Comments-on-Bitcoin-and-Ethereum-Will-a-Bullish-Rally-Come",
          "publishedOn": "2024-01-20T09:32:05.000Z",
          "wordCount": null,
          "title": "il Capo Comments on Bitcoin and Ethereum: Will a Bullish Rally Come?",
          "imageUrl": null
        },
        {
          "id": "https://cryptopanic.com/news/19190012/BTC-ETH-LINK-Get-Whales-Attention-as-Market-Eyes-Strong-Revival",
          "author": null,
          "description": "",
          "link": "https://cryptopanic.com/news/19190012/BTC-ETH-LINK-Get-Whales-Attention-as-Market-Eyes-Strong-Revival",
          "publishedOn": "2024-01-20T09:24:16.000Z",
          "wordCount": null,
          "title": "BTC, ETH, LINK Get Whales’ Attention as Market Eyes Strong Revival",
          "imageUrl": null
        },
        {
          "id": "https://cryptopanic.com/news/19190001/3-cryptocurrencies-under-1-to-buy-next-week",
          "author": null,
          "description": "The cryptocurrency market is experiencing bearish sentiments in the short term, primarily driven by Bitcoin (BTC), which is presently struggling … Continue reading",
          "link": "https://cryptopanic.com/news/19190001/3-cryptocurrencies-under-1-to-buy-next-week",
          "publishedOn": "2024-01-20T09:15:59.000Z",
          "wordCount": 596,
          "title": "3 cryptocurrencies under $1 to buy next week",
          "imageUrl": "https://assets.finbold.com/uploads/2024/01/3-cryptocurrencies-under-1-to-buy-next-week-2.jpg"
        },
        {
          "id": "https://cryptopanic.com/news/19190003/BlackRock-Has-No-Plans-to-Launch-A-XRP-Spot-ETF",
          "author": null,
          "description": "BlackRock not launching XRP ETF despite rumors; The firm focuses on Bitcoin, and Ether ETFs.",
          "link": "https://cryptopanic.com/news/19190003/BlackRock-Has-No-Plans-to-Launch-A-XRP-Spot-ETF",
          "publishedOn": "2024-01-20T09:11:24.000Z",
          "wordCount": 598,
          "title": "BlackRock Has No Plans to Launch A XRP Spot ETF",
          "imageUrl": "https://a.storyblok.com/f/182479/1792x1024/c7f4f56c94/dall-e-2024-01-20-10-09-01-a-realistic-image-of-an-investor-reading-a-newspaper-the-investor-is-portrayed-as-focused-and-engaged-sitting-comfortably-in-a-business-setting-the.webp"
        },
        {
          "id": "https://cryptopanic.com/news/19189998/Elon-Musk-Goes-Wow-After-Ark-Invest-CEO-Cathie-Wood-Points-Out-Bitcoin-Is-Backed-By-The-Largest-Computer-Network",
          "author": null,
          "description": "Billionaire Elon Musk expressed surprise after Ark Invest CEO Cathie Wood pointed out that Bitcoin (CRYPTO: BTC) is \"backed by the largest computer network\" in the world. read more",
          "link": "https://cryptopanic.com/news/19189998/Elon-Musk-Goes-Wow-After-Ark-Invest-CEO-Cathie-Wood-Points-Out-Bitcoin-Is-Backed-By-The-Largest-Computer-Network",
          "publishedOn": "2024-01-20T09:03:25.000Z",
          "wordCount": 608,
          "title": "Elon Musk Goes 'Wow' After Ark Invest CEO Cathie Wood Points Out Bitcoin Is 'Backed By The Largest Computer Network'",
          "imageUrl": "https://cdn.benzinga.com/files/images/story/2024/musk-wood-shutter.jpeg?width=1200&height=800&fit=crop"
        },
        {
          "id": "https://cryptopanic.com/news/19189946/ERC-3643-Association-Introduces-UI-Tool-for-Integrating-Regulated-Assets-with-DeFi-Platforms",
          "author": null,
          "description": "",
          "link": "https://cryptopanic.com/news/19189946/ERC-3643-Association-Introduces-UI-Tool-for-Integrating-Regulated-Assets-with-DeFi-Platforms",
          "publishedOn": "2024-01-20T08:27:21.000Z",
          "wordCount": null,
          "title": "ERC-3643 Association Introduces  UI Tool for Integrating Regulated Assets with DeFi Platforms",
          "imageUrl": null
        },
        {
          "id": "https://cryptopanic.com/news/19189938/Bitcoin-Whale-Addresses-Hit-15-Month-High-A-Sign-Of-Growing-Accumulation",
          "author": null,
          "description": "",
          "link": "https://cryptopanic.com/news/19189938/Bitcoin-Whale-Addresses-Hit-15-Month-High-A-Sign-Of-Growing-Accumulation",
          "publishedOn": "2024-01-20T08:20:14.000Z",
          "wordCount": null,
          "title": "Bitcoin Whale Addresses Hit 15-Month High – A Sign Of Growing Accumulation?",
          "imageUrl": null
        },
        {
          "id": "https://cryptopanic.com/news/19189943/Bitcoins-Hash-Rate-Soars-to-Record-Heights-ARK-Invest-Researcher-Explains-What-This-Means",
          "author": null,
          "description": "",
          "link": "https://cryptopanic.com/news/19189943/Bitcoins-Hash-Rate-Soars-to-Record-Heights-ARK-Invest-Researcher-Explains-What-This-Means",
          "publishedOn": "2024-01-20T08:14:40.000Z",
          "wordCount": null,
          "title": "Bitcoin’s Hash Rate Soars to Record Heights, ARK Invest Researcher Explains What This Means",
          "imageUrl": null
        }
      ]
    },
    {
      "title": "海外加密资讯 via shengchao shi on Inoreader",
      "feedUrl": "https://www.inoreader.com/stream/user/1005336866/tag/%E6%B5%B7%E5%A4%96%E5%8A%A0%E5%AF%86%E8%B5%84%E8%AE%AF",
      "siteUrl": "https://www.inoreader.com/stream/user/1005336866/tag/%E6%B5%B7%E5%A4%96%E5%8A%A0%E5%AF%86%E8%B5%84%E8%AE%AF/view/html",
      "articles": [
        {
          "id": "http://www.inoreader.com/article/3a9c6e74f2785f29",
          "author": "Terence Zimwara",
          "description": "Over the past five years, the number of established developers with more than 2 years experience of working in crypto grew at an annualized rate of 52%. According to the findings of a study, established developers (2+ years) together with emerging developers make an average of three times more code commits than newcomers.\n \nExperienced Developers’ Contributions\n \n“According to Electric Capital’s 2023 Crypto Developer report, the number of established active developers, or those with 2+ years of experience working on crypto-related projects, has grown by an annualized rate of 52% over the past 5 years. This annualized growth rate was achieved despite the 24% drop in the overall number of active developers from 29,611 in December 2022 to 22,411 by December 2023.\n \nThe report data also shows …",
          "link": "https://news.bitcoin.com/study-shows-number-of-crypto-developers-up-by-52-since-2018/",
          "publishedOn": "2024-01-20T11:05:53.000Z",
          "wordCount": 193,
          "title": "Study Shows Number of Crypto Developers Up by 52% Since 2018",
          "imageUrl": "https://static.news.bitcoin.com/wp-content/uploads/2024/01/shutterstock_2087017462-1.jpg"
        },
        {
          "id": "http://www.inoreader.com/article/3a9c6e74f27a43bf",
          "author": "Christian Encila",
          "description": "Justice caught up with crypto scam architect Marco Ruiz Ocho on Friday, as he received a five-year prison sentence for his role in orchestrating the IcomTech Ponzi scheme.\n \nThe ruling marks a significant victory for investors swindled out of millions and serves as a stark warning to bad actors in the burgeoning, and often unregulated, world of crypto.\n \nOchoa, 35, the former CEO of IcomTech, pleaded guilty to wire fraud charges stemming from his involvement in the elaborate scheme. Posing as a legitimate cryptocurrency mining and trading enterprise, IcomTech enticed investors with promises of daily returns on investments in non-existent crypto products.\n \nFooling People In Another Crypto Fraud\n \nThe company operated like a textbook Ponzi scheme, using new investor funds to pay off earlier…",
          "link": "https://bitcoinist.com/crypto-fraud-icomtech-ex-ceo-gets-5-years-jail/",
          "publishedOn": "2024-01-20T10:47:27.000Z",
          "wordCount": 5034,
          "title": "Crypto Fraud: IcomTech Ex-CEO Gets 5 Years Jail For Duping Investors",
          "enclosure": {
            "length": "1337",
            "type": "image/jpeg",
            "url": "https://bitcoinist.com/wp-content/uploads/2024/01/a_821d75.png?fit=318,210"
          },
          "imageUrl": "https://bitcoinist.com/wp-content/uploads/2024/01/a_821d75.png?fit=318,210"
        },
        {
          "id": "http://www.inoreader.com/article/3a9c6e74f27aca68",
          "author": "Ivan Makedonski",
          "description": "The challenges associated with physical work and delayed payments, as discussed in the construction and logistics industries articles, might not be as directly applicable to industries with less physical movement. However, the principles of instant settlement and the removal of intermediaries can still bring efficiency and innovation to various sectors. The advantages of instant settlement, such as reduced transaction fees, faster payment processing, and increased transparency, can positively impact industries beyond the physical realm. Whether it's in the realm of digital services, intellectual property, or other sectors that are already dematerialized, the application of instant settlement principles can streamline transactions and enhance overall efficiency.\nNavigating The Written Odyss…",
          "link": "https://bitcoinmagazine.com/technical/instant-settlement-series-the-publishing-industry",
          "publishedOn": "2024-01-20T10:42:43.000Z",
          "wordCount": null,
          "title": "Instant Settlement Series: The Publishing Industry",
          "enclosure": {
            "length": "1337",
            "type": "image/png",
            "url": "https://bitcoinmagazine.com/.image/c_fit,cs_srgb,q_auto:good,w_620/MjAzNzU4MzA5NjA0MzM3MTQ3/image1.png"
          },
          "imageUrl": "https://bitcoinmagazine.com/.image/c_fit,cs_srgb,q_auto:good,w_620/MjAzNzU4MzA5NjA0MzM3MTQ3/image1.png"
        },
        {
          "id": "http://www.inoreader.com/article/3a9c6e74f2610624",
          "author": "Opeyemi Sule",
          "description": "According to a recent filing, the United States Securities and Exchange Commission (SEC) has opened a comment period on Nasdaq’s proposal to allow options trading on BlackRock’s Bitcoin spot ETF (exchange-traded fund). \n \nOptions Trading On BlackRock’s Bitcoin ETF Could Come Before February End: Analyst\n \nOn Friday, January 19, the SEC acknowledged the proposal by Nasdaq to list and trade options on BlackRock’s Bitcoin spot ETF. The financial regulator asked for public comments over a 21-day period on Nasdaq’s application for options trading on BlackRock’s iShares Bitcoin Trust (IBIT).\n \nA part of the filing read: \n \n\nThe Exchange proposes to amend Options 4, Section 3, Criteria for Underlying Securities, to allow the Exchange to list and trade options on iShares Bitcoin Trust (the “Trust”…",
          "link": "https://bitcoinist.com/is-options-trading-on-blackrock-bitcoin-spot-etf/",
          "publishedOn": "2024-01-20T09:38:50.000Z",
          "wordCount": 5151,
          "title": "Is Options Trading On BlackRock’s Bitcoin Spot ETF Imminent? Here’s What We Know",
          "enclosure": {
            "length": "1337",
            "type": "image/jpeg",
            "url": "https://bitcoinist.com/wp-content/uploads/2024/01/2024-01-20-05.06.03.jpg?fit=640,410"
          },
          "imageUrl": "https://bitcoinist.com/wp-content/uploads/2024/01/2024-01-20-05.06.03.jpg?fit=640,410"
        },
        {
          "id": "http://www.inoreader.com/article/3a9c6e74f263f1db",
          "author": "David Sencil",
          "description": "A new report details how Ordinals and other layer-two innovations can reshape Bitcoin’s role in the digital economy, moving it beyond just a store of value.\n \nNew Report Outlines How Bitcoin Can Evolve to a Multi-Layered Ecosystem\n \nThe “Bitcoin Layers” report, produced by the Singapore-based web3 investment firm Spartan Group, provides an insightful look into the potential future of Bitcoin.\n \nThe report points out that bitcoin’s market capitalization, now exceeding $850 billion, has a significant portion of capital that remains underutilized due to challenges in programmability, scalability, and community alignment. It posits that Bitcoin can evolve beyond a mere store of value, transitioning into a foundational platform for a trustless financial system.\n \nA key development in this trans…",
          "link": "https://news.bitcoin.com/spartan-groups-report-reveals-bitcoins-untapped-potential-via-emerging-layers/",
          "publishedOn": "2024-01-20T09:07:52.000Z",
          "wordCount": 215,
          "title": "Spartan Group’s Report Reveals Bitcoin’s Untapped Potential via Emerging Layers",
          "imageUrl": "https://static.news.bitcoin.com/wp-content/uploads/2024/01/spartan_group_btc_layer_two.jpg"
        },
        {
          "id": "http://www.inoreader.com/article/3a9c6e74f256a326",
          "author": "David Sencil",
          "description": "Chainalysis’ latest report reveals a dual trend in the 2023 crypto crime landscape: a notable decrease in overall value of criminal transactions and a surprising shift from bitcoin to stablecoins as the preferred medium for illicit activities.\n \n2024 Chainalysis Report Reveals a Decline in Crypto Criminal Activity, Shift in Currency Preference to Stablecoins\n \nIn a revealing analysis of the cryptocurrency landscape, the 2024 Crypto Crime Trends Report by Chainalysis has potentially revealed shifts in the pattern of illicit activities within the digital currency space. The report, which provides a still-developing view of crypto-related crimes in 2023, has highlighted a notable decrease in the overall volume of criminal transactions, alongside a turn towards stablecoins by cybercriminals.\n …",
          "link": "https://news.bitcoin.com/chainalysis-reveals-decline-in-crypto-crime-shift-to-stablecoins-in-2024-crime-report/",
          "publishedOn": "2024-01-20T07:08:47.000Z",
          "wordCount": 230,
          "title": "Chainalysis Reveals Decline in Crypto Crime, Shift to Stablecoins in 2024 Crime Report",
          "imageUrl": "https://static.news.bitcoin.com/wp-content/uploads/2024/01/chainalysis_crime_report.jpg"
        },
        {
          "id": "http://www.inoreader.com/article/3a9c6e74f25078a3",
          "author": "Semilore Faleti",
          "description": "The US Commodity Futures Trading Commission (CFTC) is filing charges against crypto exchange Debiex over allegations of a $2.3 million romance scam. The US regulator announced this civil lawsuit on January 19 after filing for an enforcement action in the US District Court for the District of Arizona. \n \n \nDebiex Alleged Romance Scam Explained\n \nAccording to the CFTC’s statement, Debiex presented itself as a crypto exchange that offered US citizens access to digital assets trading features. However, the entire set-up was a ruse targeted at ripping Asian Americans of their investments using the blueprint of a romance scam. \n \nThe CFTC describes Debiex’s operations as a “sophisticated fraudulent scheme” that involved three groups of actors. These included “solicitors,” who were individuals wh…",
          "link": "https://bitcoinist.com/cftc-lawsuit-debiex-over-2-3-million-romance-scam/",
          "publishedOn": "2024-01-20T06:47:10.000Z",
          "wordCount": 5041,
          "title": "CFTC Files Lawsuit Against Debiex Over $2.3 Million Romance Scam",
          "enclosure": {
            "length": "1337",
            "type": "image/jpeg",
            "url": "https://bitcoinist.com/wp-content/uploads/2024/01/taking-legal-action-against-online-scams.jpg.optimal.jpg?fit=630,420"
          },
          "imageUrl": "https://bitcoinist.com/wp-content/uploads/2024/01/taking-legal-action-against-online-scams.jpg.optimal.jpg?fit=630,420"
        },
        {
          "id": "http://www.inoreader.com/article/3a9c6e74f25e5018",
          "author": "Sergio Goschenko",
          "description": "The Tokenized Asset Coalition (TAC), a membership organization that promotes the institutional adoption of tokenization practices to bring real-world assets to the blockchain, has published its State of Tokenization report. The document explains that 2023 saw the birth of a tokenized risk curve, with tokenization being applied to different asset classes, and predicts that its adoption will grow in 2024.\nTokenized Asset Coalition Predicts Tokenization Advances In 2024\nThe Tokenized Asset Coalition (TAC, a membership organization that advocates for bringing assets to the blockchain, predicts the advance of tokenization practices on all sides of the asset class spectrum. In its 2024 “State of Tokenization” report, the organization describes the emergence of a new tokenized risk curve that inc…",
          "link": "https://news.bitcoin.com/tokenized-asset-coalition-expects-tokenization-to-grow-in-2024/",
          "publishedOn": "2024-01-20T05:39:18.000Z",
          "wordCount": 225,
          "title": "Tokenized Asset Coalition Expects Tokenization to Grow in 2024",
          "imageUrl": "https://static.news.bitcoin.com/wp-content/uploads/2024/01/e6a78dd8-dfff-4ad5-9910-4d54c4e46b5f-1.jpg"
        },
        {
          "id": "http://www.inoreader.com/article/3a9c6e74f25b49fa",
          "author": "Samuel Edyme",
          "description": "Binance, the world’s leading digital asset exchange, has exhibited resilience and growth following its recent settlement with the US regulatory bodies. The settlement, which addressed allegations of money laundering and sanctions evasion, marked a pivotal moment for Binance.\n \nSince November 21, when the settlement was reached, Binance has experienced a surge in net inflows, amounting to roughly $4.6 billion. This data, revealed in a post by Satoshi Club on X, shows the platform’s resilience amid these challenges.\n \n \n Despite recent legal challenges and leadership changes, @binance has seen net inflows of $4.6 billion since its November settlement with US agencies.\n \nIn January alone, it attracted $3.5 billion, marking its strongest month since November 2022. pic.twitter.com/hMZZB3kK3U\n \n…",
          "link": "https://bitcoinist.com/binance-bounces-back-over-4-billion-inflow-recorded/",
          "publishedOn": "2024-01-20T04:36:51.000Z",
          "wordCount": 5050,
          "title": "Binance Bounces Back: Over $4 Billion Inflow Recorded Post-Settlement",
          "enclosure": {
            "length": "1337",
            "type": "image/jpeg",
            "url": "https://bitcoinist.com/wp-content/uploads/2023/02/Binance.jpg?fit=350,250"
          },
          "imageUrl": "https://bitcoinist.com/wp-content/uploads/2023/02/Binance.jpg?fit=350,250"
        },
        {
          "id": "http://www.inoreader.com/article/3a9c6e74f24553c9",
          "author": "Kevin Helms",
          "description": "The head of India’s central bank, the Reserve Bank of India (RBI), has warned of significant risks associated with cryptocurrencies, particularly for emerging market economies. “It can impact your financial stability, currency stability, and monetary system,” RBI Governor Shaktikanta Das said.\n \nRBI Governor’s Crypto Warnings\n \nShaktikanta Das, the governor of India’s central bank, the Reserve Bank of India (RBI), issued several warnings regarding cryptocurrency at the World Economic Forum in Davos this week. Das said:\n \n\nCryptocurrencies have huge risk, particularly for emerging market economies because it can impact your financial stability, currency stability, and monetary system.\n \n“There is no underlying. It is not a currency, but it has the potential to become a currency in which eve…",
          "link": "https://news.bitcoin.com/rbi-chief-crypto-threatens-rupee-stability-urges-investors-to-be-cautious/",
          "publishedOn": "2024-01-20T04:09:55.000Z",
          "wordCount": 206,
          "title": "RBI Chief: Crypto Threatens Rupee Stability, Urges Investors to Be Cautious",
          "imageUrl": "https://static.news.bitcoin.com/wp-content/uploads/2024/01/rbi-gov.jpg"
        },
        {
          "id": "http://www.inoreader.com/article/3a9c6e74f2471f4b",
          "author": "Nikhilesh De",
          "description": "Last summer, the U.S. Securities and Exchange Commission (SEC) sued crypto exchanges Coinbase and Binance, alleging they listed and traded unregistered securities in the form of various cryptocurrencies. This week, the regulator's legal teams faced the exchanges in court as the companies argued the SEC did not make the case that those cryptos are securities.",
          "link": "https://www.coindesk.com/policy/2024/01/20/the-sec-goes-back-to-court/?utm_medium=referral&utm_source=rss&utm_campaign=headlines",
          "publishedOn": "2024-01-20T03:47:16.000Z",
          "wordCount": 11753,
          "title": "The SEC Goes Back to Court",
          "enclosure": {
            "length": "1337",
            "type": "image/jpeg",
            "url": "https://www.coindesk.com/resizer/CBxIi9FIHMFrW6BSz_wiMHizyag=/800x600/cloudfront-us-east-1.images.arcpublishing.com/coindesk/WRJFKVPZAJBETOLVR3ZZMPOXW4.jpg"
          },
          "imageUrl": "https://www.coindesk.com/resizer/CBxIi9FIHMFrW6BSz_wiMHizyag=/800x600/cloudfront-us-east-1.images.arcpublishing.com/coindesk/WRJFKVPZAJBETOLVR3ZZMPOXW4.jpg"
        },
        {
          "id": "http://www.inoreader.com/article/3a9c6e74f24264c4",
          "author": "Ronaldo Marquez",
          "description": "As the legal battle unfolds between the United States Securities and Exchange Commission (SEC) and US-based crypto exchange Coinbase, the presiding Judge Katherine Polk Failla has shown skepticism towards the SEC’s position and motives in pursuing the case. \n \nThis development has tilted the scales in favor of Coinbase, as the judge demonstrated a keen interest and indicated a potential inclination towards the exchange’s arguments.\n \nCoinbase’s Defense Gains Momentum\n \nThe SEC filed a lawsuit against Coinbase in June, alleging that the exchange facilitated trading of crypto tokens that should have been registered as securities. \n \nSpecifically, the SEC accused Coinbase of operating as an unregistered national securities exchange, broker, and clearing agency. \n \nThe regulatory body took par…",
          "link": "https://bitcoinist.com/coinbase-70-chance-of-victory-against-sec/",
          "publishedOn": "2024-01-20T03:05:46.000Z",
          "wordCount": 5114,
          "title": "Coinbase Poised For Success? Bloomberg’s Legal Expert Gives 70% Chance Of Victory Against SEC",
          "enclosure": {
            "length": "1337",
            "type": "image/jpeg",
            "url": "https://bitcoinist.com/wp-content/uploads/2024/01/shutterstock_download-2-34.jpg?fit=390,260"
          },
          "imageUrl": "https://bitcoinist.com/wp-content/uploads/2024/01/shutterstock_download-2-34.jpg?fit=390,260"
        },
        {
          "id": "http://www.inoreader.com/article/3a9c6e74f24cd465",
          "author": "Kevin Helms",
          "description": "U.S. lawmakers have introduced a bill “to combat the illicit use of crypto assets.” The Preventing Illicit Finance Through Partnership Act “will allow federal regulators to work with the private sector to gain insight into the often-misunderstood world of crypto to weed out bad actors without crushing an entire emerging industry,” Senator Cynthia Lummis described.\n \nPreventing Illicit Finance Through Partnership Act 2024\n \nU.S. Senators Bill Hagerty (R-TN) and Cynthia Lummis (R-WY) introduced the Preventing Illicit Finance Through Partnership Act of 2024 on Wednesday. Hagerty and Lummis are members of the Senate Banking Committee.\n \nThe bill seeks to “establish an information-sharing pilot program to combat the illicit use of crypto assets,” according to the bill’s text. The legislation ta…",
          "link": "https://news.bitcoin.com/us-senators-introduce-bill-to-combat-illicit-use-of-crypto-assets-through-public-private-partnership/",
          "publishedOn": "2024-01-20T02:36:02.000Z",
          "wordCount": 222,
          "title": "US Senators Introduce Bill ‘to Combat Illicit Use of Crypto Assets’ Through Public-Private Partnership",
          "imageUrl": "https://static.news.bitcoin.com/wp-content/uploads/2024/01/illicit-finance-bill.jpg"
        },
        {
          "id": "http://www.inoreader.com/article/3a9c6e74f249c045",
          "author": "Keshav Verma",
          "description": "A few days since the Bitcoin spot ETFs have gone live, here are the winners and losers in the space, as an analyst broke down.\n \nBlackrock’s iShares Bitcoin ETF Is The Biggest Winner So Far\n \nEarlier in the month, the much-anticipated Bitcoin spot ETFs finally gained approval from the US SEC. The BTC spot ETFs are financial instruments that allow investors to gain indirect exposure to the cryptocurrency’s price movements.\n \nThis means that, with the spot ETF, traders don’t need to own the asset itself to gain exposure to it. ETFs trade on traditional exchanges, so they may be a preferable option for traditional investors.\n \n \nFor some investors, navigating cryptocurrency exchanges and learning how wallets work may be a market entry barrier. Still, with the ETFs, such traders should also be…",
          "link": "https://bitcoinist.com/bitcoin-spot-etfs-analyst-everything-need-know/",
          "publishedOn": "2024-01-20T01:34:57.000Z",
          "wordCount": 5107,
          "title": "Bitcoin Spot ETFs: Analyst Lists Everything You Need To Know",
          "enclosure": {
            "length": "1337",
            "type": "image/jpeg",
            "url": "https://bitcoinist.com/wp-content/uploads/2024/01/kanchanara-9pCV2MB65y8-unsplash.jpg?fit=630,420"
          },
          "imageUrl": "https://bitcoinist.com/wp-content/uploads/2024/01/kanchanara-9pCV2MB65y8-unsplash.jpg?fit=630,420"
        },
        {
          "id": "http://www.inoreader.com/article/3a9c6e74f23401b2",
          "author": "Sergio Goschenko",
          "description": "A bill that seeks to safeguard the cryptocurrency rights of the citizens has been introduced to the Senate of Virginia. The bill, sponsored by State Sen. Saddam Azlan Salim, would guarantee that citizens can self-custody, transact, mine, and pay with cryptocurrency, also exempting cryptocurrency transactions of less than $200 from paying state capital gains tax.\nVirginia State Senator Introduces Cryptocurrency Rights Bill\nSaddam Azlan Salim, a state senator in Virginia, has introduced a bill that aims to impede state authorities from blocking its citizens from exerting different cryptocurrency and bitcoin-linked activities. Senate Bill 339 (SB 339), introduced on January 9, establishes that citizens will not require a money-transferring license to operate staking or mining equipment at the…",
          "link": "https://news.bitcoin.com/cryptocurrency-rights-bill-introduced-in-virginia/",
          "publishedOn": "2024-01-20T01:06:30.000Z",
          "wordCount": 209,
          "title": "Cryptocurrency Rights Bill Introduced in Virginia",
          "imageUrl": "https://static.news.bitcoin.com/wp-content/uploads/2024/01/f3a23e71-51fa-46c3-bceb-2e68bdd3b15a.jpg"
        },
        {
          "id": "http://www.inoreader.com/article/3a9c6e74f2316eb5",
          "author": "Scott Matherson",
          "description": "One crypto trader has been making the rounds on social media after making more than $6 million in profit on the Ethereum blockchain. This incredible trade took place in less than a day, translating to an almost 600% gain for the whale trade. So how did they do this?\n \nCrypto Trader Makes $6.7 Million In 3 Hours\n \nAccording to Lookonchain, an on-chain data tracker, a single wallet has made almost $7 million off a particularly hyped launch in the last day. The project, Satoshi VM which is a Layer 2 network for the Bitcoin blockchain, launched on Thursday amid much fanfare as it was shilled by some notable influencers in the space.\n \n \nOne wallet, in particular, took advantage of this hyped launch and paid a premium fee to snipe the launch. As Lookonchain reports, the trader paid a bribe fee …",
          "link": "https://bitcoinist.com/crypto-trader-6-7-million-ethereum/",
          "publishedOn": "2024-01-20T00:03:45.000Z",
          "wordCount": 5121,
          "title": "Crypto Trader Makes $6.7 Million In 3 Hours With Ethereum Token, Here’s How",
          "enclosure": {
            "length": "1337",
            "type": "image/jpeg",
            "url": "https://bitcoinist.com/wp-content/uploads/2024/01/Crypto-trader-Ethereum-SAVM-Small.jpeg?fit=320,180"
          },
          "imageUrl": "https://bitcoinist.com/wp-content/uploads/2024/01/Crypto-trader-Ethereum-SAVM-Small.jpeg?fit=320,180"
        },
        {
          "id": "http://www.inoreader.com/article/3a9c6e74f233e9c8",
          "author": "Jamie Redman",
          "description": "The integration of artificial intelligence (AI) and cryptocurrency is heralding a new era of technological advancement, as highlighted in a recent Grayscale Investments report by Will Ogden Moore. Grayscale’s latest report says this synergy, marked by the impressive performance of AI-related crypto assets, is expanding the scope of blockchain applications beyond traditional payment systems. \n \nGrayscale Research Report Illuminates the Collaborative Future of AI and Cryptocurrency\n \nGrayscale Investments’ research report emphasizes the potential of this intersection to address future AI-related societal challenges, including concerns over data privacy and the centralization of power. According to the Grayscale researcher, Will Ogden Moore, AI-adjacent cryptocurrencies have shown significant…",
          "link": "https://news.bitcoin.com/grayscales-new-study-reveals-emerging-synergy-between-ai-and-cryptocurrency/",
          "publishedOn": "2024-01-19T23:38:45.000Z",
          "wordCount": 224,
          "title": "Grayscale’s New Study Reveals Emerging Synergy Between AI and Cryptocurrency",
          "imageUrl": "https://static.news.bitcoin.com/wp-content/uploads/2024/01/brainbtc.jpg"
        },
        {
          "id": "http://www.inoreader.com/article/3a9c6e74f23997cd",
          "author": "Dalmas Ngetich",
          "description": "In a post on X, analyst Cardano Yoda believes that a USD-pegged stablecoin is crucial for ADA’s future success, suggesting that its integration could trigger a bull run sometime in 2025.\n \nA stablecoin, a token that’s “stable” since its price is pegged to a fiat currency like the USD or Euro, will ignite activity, driving decentralized finance (DeFi) and even non-fungible token (NFT) activities even higher. With a popular stablecoin like USDT or USDC deployed on the proof-of-stake blockchain, the number of users interacting with Cardano dapps will likely spike, catalyzing demand since ADA is used for paying fees.\n \nStablecoins, Input Endorsers, And Hydra Might Prop Up Cardano In The Long-Term\n \nThe presence of a high market cap stablecoin can facilitate seamless value transfers and reduce …",
          "link": "https://bitcoinist.com/cardano-usd-backed-stablecoin-like-usdt-to-rally/",
          "publishedOn": "2024-01-19T22:39:58.000Z",
          "wordCount": 5114,
          "title": "Is It True That Cardano Needs A “USD-Backed Stablecoin” Like USDT To Rally?",
          "enclosure": {
            "length": "1337",
            "type": "image/jpeg",
            "url": "https://bitcoinist.com/wp-content/uploads/2024/01/Crypto-news-Template168.jpg?fit=640,362"
          },
          "imageUrl": "https://bitcoinist.com/wp-content/uploads/2024/01/Crypto-news-Template168.jpg?fit=640,362"
        },
        {
          "id": "http://www.inoreader.com/article/3a9c6e74f23b76a3",
          "author": "Daniel Kuhn",
          "description": "Response to the latest article misunderstanding bitcoin.",
          "link": "https://www.coindesk.com/consensus-magazine/2024/01/19/the-new-york-times-still-doesnt-get-bitcoin/?utm_medium=referral&utm_source=rss&utm_campaign=headlines",
          "publishedOn": "2024-01-19T22:21:59.000Z",
          "wordCount": 14910,
          "title": "The New York Times Still Doesn’t Get Bitcoin",
          "enclosure": {
            "length": "1337",
            "type": "image/jpeg",
            "url": "https://www.coindesk.com/resizer/TR72VXllKX0V3e2ckVUNeD6hWic=/800x600/cloudfront-us-east-1.images.arcpublishing.com/coindesk/4WS3755O5NBQPHJQJE7T42HFQE.jpg"
          },
          "imageUrl": "https://www.coindesk.com/resizer/TR72VXllKX0V3e2ckVUNeD6hWic=/800x600/cloudfront-us-east-1.images.arcpublishing.com/coindesk/4WS3755O5NBQPHJQJE7T42HFQE.jpg"
        },
        {
          "id": "http://www.inoreader.com/article/3a9c6e74f224da5b",
          "author": "Sergio Goschenko",
          "description": "Coinbase, a U.S based cryptocurrency exchange, and the U.S. Securities and Exchange Commission (SEC) had their first scuffle as New York’s Judge Katherine Polk Failla weighted in on a motion to dismiss the case in which the regulator alleges the exchange was involved in facilitating the trade of unregistered securities. Judge Failla will decide on the subject in the coming weeks.\nCoinbase and SEC Face at Court\nWhat might become the most significant case to define the classification of cryptocurrencies as securities finished its first chapter without a clear winner. This Wednesday, Coinbase and the U.S. Securities and Exchange Commission (SEC) met for the first time in court to discuss if the case should be thrown based on the arguments presented by the exchange in a document filed in Augus…",
          "link": "https://news.bitcoin.com/security-definition-at-the-core-of-coinbase-v-sec-first-scuffle/",
          "publishedOn": "2024-01-19T22:06:42.000Z",
          "wordCount": 236,
          "title": "Security Definition at the Core of Coinbase v SEC First Scuffle",
          "imageUrl": "https://static.news.bitcoin.com/wp-content/uploads/2024/01/8da17bb8-84ad-4c47-9eb5-bf15b71160b8.jpg"
        }
      ]
    }
  ],
  "cliVersion": "1.15.1"
}